{
  "enabled": true,
  "campaign": {
    "enabled": true,
    "badge": "New Store Sale",
    "title": "NEWSTORE Sale - Up to 25% OFF",
    "subtitle": "All premium FiveM & Clothing items are on sale",
    "description": "Get the most advanced FiveM scripts at unbelievable prices. All scripts include lifetime updates and special support.",
    "cta": {
      "label": "Start Shopping",
      "url": "/store"
    },
    "secondaryCta": {
      "label": "Details",
      "url": "/blog"
    },
    "endsAt": "2026-07-01T23:59:00Z",
    "color": "cyan",
    "showConfetti": false
  },
  "discount": {
    "enabled": false,
    "badge": "%25 İndirim",
    "label": "25% Discount",
    "description": "All products"
  },
  "coupon": {
    "enabled": true,
    "code": "NEWSTORE",
    "label": "Coupon Code",
    "description": "Apply at checkout",
    "copyable": true
  },
  "announcement": {
    "enabled": true,
    "icon": "🎉",
    "title": "Crosshair Script Released!",
    "body": "The advanced & optimized Crosshair script is now available in our store!",
    "link": {
      "label": "Check it out",
      "url": "/product/7549331"
    }
  }
}
